replanaii/__init__.py
replanaii/dom.py
replanaii/expr.py
replanaii/mesh.py
replanaii/replanaii.cp310-win_amd64.pyd
replanaii-0.1.4.data/data/README/README.md
replanaii-0.1.4.data/data/licenses/APACHE2
replanaii-0.1.4.data/data/licenses/MIT
replanaii-0.1.4.dist-info/LICENSE
replanaii-0.1.4.dist-info/METADATA
replanaii-0.1.4.dist-info/WHEEL
replanaii-0.1.4.dist-info/top_level.txt
replanaii-0.1.4.dist-info/RECORD
